lib_attacher/__init__.py
lib_attacher-0.0.1.dist-info/METADATA
lib_attacher-0.0.1.dist-info/WHEEL
lib_attacher-0.0.1.dist-info/license
lib_attacher-0.0.1.dist-info/top_level.txt
lib_attacher-0.0.1.dist-info/RECORD
