Metadata-Version: 2.1
Name: lib-attacher
Version: 0.0.1
Summary: A simple library for finding a superordinate path and attaching it to the module search path.
Home-page: https://github.com/adaviding/lib_attacher
Author: David Ing
Author-email: ing.dave@gmail.com
License: UNKNOWN
Platform: UNKNOWN
Classifier: Programming Language :: Python :: 3
Classifier: License :: OSI Approved :: MIT License
Classifier: Operating System :: OS Independent
Requires-Python: >=3.6
